<?xml version="1.0" ?>
<?xml-stylesheet href="../style/nmap.xsl" type="text/xsl"?>
<nmaprun scanner="nmap" args="nmap -sS -sU -A --stylesheet ../style/nmap.xsl -oA /var/www/secure/nmap/2009-09-01T01:00:01/nmap fred" start="1251763201" startstr="Tue Sep  1 01:00:01 2009" version="4.11" xmloutputversion="1.01">
<scaninfo type="syn" protocol="tcp" numservices="1680" services="1-1027,1029-1033,1040,1043,1050,1058-1059,1067-1068,1076,1080,1083-1084,1103,1109-1110,1112,1127,1139,1155,1158,1178,1212,1214,1220,1222,1234,1241,1248,1337,1346-1381,1383-1552,1600,1650-1652,1661-1672,1680,1720,1723,1755,1761-1764,1827,1900,1935,1984,1986-2028,2030,2032-2035,2038,2040-2049,2053,2064-2065,2067-2068,2105-2106,2108,2111-2112,2120-2121,2201,2232,2241,2301,2307,2401,2430-2433,2500-2501,2564,2600-2605,2627-2628,2638,2766,2784,2809,2903,2998,3000-3001,3005-3006,3049,3052,3064,3086,3128,3141,3264,3268-3269,3292,3306,3333,3372,3389,3421,3455-3457,3462,3531,3632,3689,3900,3984-3986,3999-4000,4002,4008,4045,4125,4132-4133,4144,4224,4321,4333,4343,4444,4480,4500,4557,4559,4660,4662,4672,4899,4987,4998,5000-5003,5010-5011,5050,5060,5100-5102,5145,5190-5193,5232,5236,5300-5305,5308,5400,5405,5432,5490,5510,5520,5530,5540,5550,5555,5560,5631-5632,5679-5680,5713-5717,5800-5803,5900-5903,5977-5979,5997-6009,6017,6050,6101,6103,6105-6106,6110-6112,6141-6148,6346-6347,6400-6401,6502,6543-6544,6547-6548,6558,6588,6666-6668,6699,6881,6969,7000-7010,7070,7100,7200-7201,7273,7326,7464,7597,7937-7938,8000,8007,8009,8021,8080-8082,8443,8888,8892,9090,9100,9111,9152,9535,9876,9991-9992,9999-10000,10005,10082-10083,11371,12000,12345-12346,13701-13702,13705-13706,13708-13718,13720-13722,13782-13783,15126,16444,16959,17007,17300,18000,18181-18185,18187,19150,20005,22273,22289,22305,22321,22370,26208,27000-27010,27374,27665,31337,31416,32770-32780,32786-32787,38037,38292,43188,44334,44442-44443,47557,49400,50000,50002,54320,61439-61441,65301" />
<scaninfo type="udp" protocol="udp" numservices="1487" services="1-1025,1028,1030-1032,1034,1043,1058-1059,1067-1068,1080,1083-1084,1110,1155,1167,1212,1214,1222,1248,1346-1381,1383-1552,1600,1645-1646,1650-1652,1661-1672,1701,1812-1813,1900,1986-2002,2004-2028,2030,2032-2035,2038,2040-2049,2065,2067,2103-2106,2108,2201,2232,2241,2307,2401,2430-2433,2500-2501,2627,2784,2948,2967,3049,3130,3141,3246,3264,3333,3401,3421,3455-3457,3531,3900,3984-3986,3996-3998,4000,4008,4045,4132-4133,4321,4343,4444,4500,4666,4672,4827,5000-5003,5010-5011,5050,5060,5145,5190-5193,5236,5300-5305,5308,5428,5500,5540,5555,5632,5713-5717,6110-6111,6141-6148,6346-6347,6502,6549,6558,6969,7000-7010,7100,7200-7201,7648-7651,9535,9876,10080,16444,17007,17185,18000,22370,26000,26900,27015,27444,27500,27910,27960,28910,31335,31337,32768,32770-32780,32786-32787,38037,38293,39213,45000,47557,54321" />
<verbose level="0" />
<debugging level="0" />
<host><status state="up" />
<address addr="192.168.0.47" addrtype="ipv4" />
<address addr="00:22:19:27:5E:28" addrtype="mac" />
<hostnames><hostname name="fred.example.com" type="PTR" /></hostnames>
<ports><extraports state="closed" count="3160" />
<port protocol="tcp" portid="80"><state state="open" /><service name="http" servicefp="SF-Port80-TCP:V=4.11%I=7%D=9/1%Time=4A9C710C%P=x86_64-redhat-linux-gnu%r(GetRequest,EA,&quot;HTTP/1\.1\x20301\x20Moved\x20Permanently\r\nDate:\x20Tue,\x201\x20Sep\x202009\x2000:55:40\x20GMT\r\nLocation:\x20https://fred\.example\.com/\r\nConnection:\x20close\r\nContent-Type:\x20text/html\r\nContent-Length:\x2056\r\n\r\n&lt;HTML&gt;&lt;BODY&gt;&lt;H1&gt;301\x20Moved\x20Permanently&lt;/H1&gt;&lt;/BODY&gt;&lt;/HTML&gt;&quot;)%r(HTTPOptions,BA,&quot;HTTP/1\.1\x20501\x20Not\x20Implemented\r\nDate:\x20Tue,\x201\x20Sep\x202009\x2000:55:40\x20GMT\r\nConnection:\x20close\r\nContent-Type:\x20text/html\r\nContent-Length:\x2054\r\n\r\n&lt;HTML&gt;&lt;BODY&gt;&lt;H1&gt;501\x20Not\x20Implemented&lt;/H1&gt;&lt;/BODY&gt;&lt;/HTML&gt;&quot;)%r(RTSPRequest,BA,&quot;HTTP/1\.1\x20501\x20Not\x20Implemented\r\nDate:\x20Tue,\x201\x20Sep\x202009\x2000:55:40\x20GMT\r\nConnection:\x20close\r\nContent-Type:\x20text/html\r\nContent-Length:\x2054\r\n\r\n&lt;HTML&gt;&lt;BODY&gt;&lt;H1&gt;501\x20Not\x20Implemented&lt;/H1&gt;&lt;/BODY&gt;&lt;/HTML&gt;&quot;)%r(FourOhFourRequest,10D,&quot;HTTP/1\.1\x20301\x20Moved\x20Permanently\r\nDate:\x20Tue,\x201\x20Sep\x202009\x2000:55:45\x20GMT\r\nLocation:\x20https://fred\.example\.com/nice%20ports%2C/Tri%6Eity\.txt%2ebak\r\nConnection:\x20close\r\nContent-Type:\x20text/html\r\nContent-Length:\x2056\r\n\r\n&lt;HTML&gt;&lt;BODY&gt;&lt;H1&gt;301\x20Moved\x20Permanently&lt;/H1&gt;&lt;/BODY&gt;&lt;/HTML&gt;&quot;);" method="table" conf="3" /></port>
<port protocol="tcp" portid="427"><state state="open" /><service name="svrloc" method="table" conf="3" /></port>
<port protocol="tcp" portid="443"><state state="open" /><service name="https" servicefp="SF-Port443-TCP:V=4.11%I=7%D=9/1%Time=4A9C7127%P=x86_64-redhat-linux-gnu%r(SSLSessionReq,301,&quot;\x16\x03\0\0\*\x02\0\0&amp;\x03\0J\x9cq\&quot;\x93\x873\\\xa3hc\xec_\xff\x94\$\x832\xd0\xdf\x04\x1eq\x0b\xb9&amp;\xa8\xfa\x90,\xab\x94\0\0\n\0\x16\x03\0\x02\xbb\x0b\0\x02\xb7\0\x02\xb4\0\x02\xb10\x82\x02\xad0\x82\x02W\xa0\x03\x02\x01\x02\x02\x08COhc61990\r\x06\t\*\x86H\x86\xf7\r\x01\x01\x05\x05\x000\x1b1\x190\x17\x06\x03U\x04\n\x13\x10VMware\x20Installer0\x1e\x17\r090807144144Z\x17\r210205144144Z0\x81\xfa1\x0b0\t\x06\x03U\x04\x06\x13\x02US1\x130\x11\x06\x03U\x04\x08\x13\nCalifornia1\x120\x10\x06\x03U\x04\x07\x13\tPalo\x20Alto1\x140\x12\x06\x03U\x04\n\x13\x0bVMware,\x20Inc1\.0,\x06\x03U\x04\x0b\x13%VMware\x20ESX\x20Server\x20Default\x20Certificate1\*0\(\x06\t\*\x86H\x86\xf7\r\x01\t\x01\x16\x1bssl-certificates@vmware\.com1\x1e0\x1c\x06\x03U\x04\x03\x13\x15localhost\.localdomain100\.\x06\t\*\x86H\x86\xf7\r\x01\t\x02\x13!1249656104,564d7761726520496e632e0\x81\x9f0\r\x06\t\*\x86H\x86\xf7\r\x01\x01\x01\x05\0\x03\x81\x8d\x000\x81\x89\x02\x81\x81\0\xc7\xb7\x02b\xdd\x02\x96\xc9\xe7\xacxm\x92v\xee\x1c\xa4\x89z\x83\)7u1\x80u6\xefX\xfe\x1a\xa8J\.\trV\x90kf\xe5N_c&gt;\x05\xed\x0e\xe8~\xda_\x20\xff\xd6\x0c&apos;GWN\^s\xf9\xeel\+p\xf6\xe4\xb26\xbd\xa0\xd38\xc0~eg\xff\xd5{\x908\xe0\x8f\xeaM#\)\x0bc\xf9\x19\xd1\xaf\x16\x02\x02\xd1\xb8\xdc\xf9\xf62A\xfa\x98\x85\xa3\x85\xf3\x98\x98n\xf7\xa5\x95&lt;g\x20B\x1c,\xc0EAK\x02\x03\x01\0\x01\xa3\[0Y0\t\x06\x03U\x1d\x13\x04\x020\x000\x0b\x06\x03U\x1d\x0f\x04\x04\x03\x02\x04\xb00\x1d\x06\x03U\x1d%\x04\x160\x14\x06\x08\+\x06\x01\x05\x05\x07\x03\x01\x06\x08\+\x06\x01\x05\x05\x07\x03\x020\x20\x06\x03U\x1d\x11\x04\x190\x17\x82\x15localhost\.localdomain0\r\x06\t\*\x86H\x86\xf7\r\x01\x01\x05\x05\0\x03A\0yA\xa6\xa9\n\xcdD\x17X1\xc9\x87\xf4a\xb7\x9a\x1f0e\xa4\)I&lt;\xfe\x8b\xe8\xcb\xc4z!~\x8b\x97\xdc\n\xec\xd9\x95\?\xac\xa7\xb12\xfb\x91F\xae\x86\&quot;\x1c\x88\x08\xa2\xd4\n\xc5\\\xa7\xa2\xba:iI\xa6\x16\x03\0\0\r\r\0\0\x05\x02\x01\x02\0\0\x0e\0\0\0&quot;);" method="table" conf="3" /></port>
<port protocol="tcp" portid="902"><state state="open" /><service name="iss-realsecure-sensor" servicefp="SF-Port902-TCP:V=4.11%I=7%D=9/1%Time=4A9C712D%P=x86_64-redhat-linux-gnu%r(NULL,73,&quot;220\x20VMware\x20Authentication\x20Daemon\x20Version\x201\.10:\x20SSL\x20Required,\x20ServerDaemonProtocol:SOAP,\x20MKSDisplayProtocol:VNC\x20,\x20\r\n&quot;)%r(GenericLines,73,&quot;220\x20VMware\x20Authentication\x20Daemon\x20Version\x201\.10:\x20SSL\x20Required,\x20ServerDaemonProtocol:SOAP,\x20MKSDisplayProtocol:VNC\x20,\x20\r\n&quot;)%r(GetRequest,73,&quot;220\x20VMware\x20Authentication\x20Daemon\x20Version\x201\.10:\x20SSL\x20Required,\x20ServerDaemonProtocol:SOAP,\x20MKSDisplayProtocol:VNC\x20,\x20\r\n&quot;)%r(HTTPOptions,73,&quot;220\x20VMware\x20Authentication\x20Daemon\x20Version\x201\.10:\x20SSL\x20Required,\x20ServerDaemonProtocol:SOAP,\x20MKSDisplayProtocol:VNC\x20,\x20\r\n&quot;)%r(RTSPRequest,73,&quot;220\x20VMware\x20Authentication\x20Daemon\x20Version\x201\.10:\x20SSL\x20Required,\x20ServerDaemonProtocol:SOAP,\x20MKSDisplayProtocol:VNC\x20,\x20\r\n&quot;)%r(RPCCheck,73,&quot;220\x20VMware\x20Authentication\x20Daemon\x20Version\x201\.10:\x20SSL\x20Required,\x20ServerDaemonProtocol:SOAP,\x20MKSDisplayProtocol:VNC\x20,\x20\r\n&quot;)%r(DNSVersionBindReq,73,&quot;220\x20VMware\x20Authentication\x20Daemon\x20Version\x201\.10:\x20SSL\x20Required,\x20ServerDaemonProtocol:SOAP,\x20MKSDisplayProtocol:VNC\x20,\x20\r\n&quot;)%r(DNSStatusRequest,73,&quot;220\x20VMware\x20Authentication\x20Daemon\x20Version\x201\.10:\x20SSL\x20Required,\x20ServerDaemonProtocol:SOAP,\x20MKSDisplayProtocol:VNC\x20,\x20\r\n&quot;)%r(Help,73,&quot;220\x20VMware\x20Authentication\x20Daemon\x20Version\x201\.10:\x20SSL\x20Required,\x20ServerDaemonProtocol:SOAP,\x20MKSDisplayProtocol:VNC\x20,\x20\r\n&quot;)%r(SSLSessionReq,81,&quot;220\x20VMware\x20Authentication\x20Daemon\x20Version\x201\.10:\x20SSL\x20Required,\x20ServerDaemonProtocol:SOAP,\x20MKSDisplayProtocol:VNC\x20,\x20\r\n\x15\x03\0\0\x02\x02\(\x15\x03\0\0\x02\x02\(&quot;)%r(SMBProgNeg,73,&quot;220\x20VMware\x20Authentication\x20Daemon\x20Version\x201\.10:\x20SSL\x20Required" method="table" conf="3" /></port>
<port protocol="tcp" portid="8000"><state state="open" /><service name="http-alt" method="table" conf="3" /></port>
<port protocol="udp" portid="123"><state state="open" /><service name="ntp" product="NTP" version="v4" method="probed" conf="10" /></port>
<port protocol="udp" portid="427"><state state="open|filtered" /><service name="svrloc" method="table" conf="3" /></port>
</ports>
<os><portused state="open" proto="tcp" portid="80" />
<portused state="closed" proto="tcp" portid="1" />
<osclass type="general purpose" vendor="FreeBSD" osfamily="FreeBSD" osgen="5.X" accuracy="100" />
<osmatch name="FreeBSD 5.2 - 5.3" accuracy="100" line="7725" />
</os>
<uptime seconds="1868723" lastboot="Mon Aug 10 10:58:52 2009" />
<tcpsequence index="9999999" class="truly random" difficulty="Good luck!" values="7012FC34,31516F34,6DB98B15,50F29E92,C91E09B3,3FFF4410" />
<ipidsequence class="Incremental" values="8EB4,8EB5,8EB6,8EB7,8EB8,8EB9" />
<tcptssequence class="100HZ" values="B2371E6,B2371F1,B2371FC,B237207,B237212,B23721D" />
</host>
<runstats><finished time="1251770609" timestr="Tue Sep  1 03:03:29 2009"/><hosts up="1" down="0" total="1" />
</runstats></nmaprun>
